jesse_portal_gun/__init__.py
jesse_portal_gun/main.py
jesse_portal_gun-0.1.0.dist-info/entry_points.txt
jesse_portal_gun-0.1.0.dist-info/WHEEL
jesse_portal_gun-0.1.0.dist-info/METADATA
jesse_portal_gun-0.1.0.dist-info/RECORD
