Metadata-Version: 2.1
Name: jesse-portal-gun
Version: 0.1.0
Summary: 
Author: Jesse Hartman
Author-email: jesse@xample.com
Requires-Python: >=3.10,<4.0
Classifier: Programming Language :: Python :: 3
Classifier: Programming Language :: Python :: 3.10
Classifier: Programming Language :: Python :: 3.11
Requires-Dist: typer[all] (>=0.6.1,<0.7.0)
